IDEA_Wrapper-0.0.1.dist-info/METADATA
IDEA_Wrapper-0.0.1.dist-info/RECORD
IDEA_Wrapper-0.0.1.dist-info/WHEEL
IDEA_Wrapper-0.0.1.dist-info/top_level.txt
idea_wrapper/__init__.py
idea_wrapper/record_set.py
idea_wrapper/table_def.py
