Metadata-Version: 2.1
Name: IDEA-Wrapper
Version: 0.0.1
Summary: A readonly wrapper for the IDEA Python integration
Home-page: UNKNOWN
Author: Alexander Baron
License: UNKNOWN
Platform: UNKNOWN
Classifier: Programming Language :: Python :: 3
Classifier: License :: OSI Approved :: MIT License
Classifier: Operating System :: OS Independent
Requires-Dist: datetime
